{
    "movies": {
        "209945": {
            "Title": "Sayen",
            "Image Source": "https://i.imgur.com/uHGfwKY.jpg",
            "Category": "movies",
            "Genres": [
                "Action"
            ],
            "Rating": "N/A",
            "TMDb ID": 850871
        },
        "209891": {
            "Title": "Love at First Kiss",
            "Image Source": "https://i.imgur.com/SflYzWe.jpg",
            "Category": "movies",
            "Genres": [
                "Romance",
                "Comedy"
            ],
            "Rating": "N/A",
            "TMDb ID": 818648
        },
        "192014": {
            "Title": "Nocebo",
            "Image Source": "https://i.imgur.com/vMwPUU9.jpg",
            "Category": "movies",
            "Genres": [
                "Thriller"
            ],
            "Rating": "5.8",
            "TMDb ID": 782936
        },
        "187330": {
            "Title": "Aftersun",
            "Image Source": "https://i.imgur.com/oqJtcFE.jpg",
            "Category": "movies",
            "Genres": [
                "Drama"
            ],
            "Rating": "7.8",
            "TMDb ID": 965150
        },
        "191323": {
            "Title": "Emily",
            "Image Source": "https://i.imgur.com/Qpqpfv7.jpg",
            "Category": "movies",
            "Genres": [
                "Drama",
                "Romance",
                "Biography"
            ],
            "Rating": "6.9",
            "TMDb ID": 862965
        },
        "209722": {
            "Title": "Tonight Youre Sleeping with Me",
            "Image Source": "https://i.imgur.com/pBKoVKb.jpg",
            "Category": "movies",
            "Genres": [
                "Drama"
            ],
            "Rating": "N/A",
            "TMDb ID": 1081313
        },
        "203856": {
            "Title": "M3gan",
            "Image Source": "https://i.imgur.com/7tlhpoD.jpg",
            "Category": "movies",
            "Genres": [
                "Thriller",
                "Sci-fi",
                "Horror"
            ],
            "Rating": "6.5",
            "TMDb ID": 536554
        },
        "209691": {
            "Title": "Saint Omer",
            "Image Source": "https://i.imgur.com/pb3JfiR.jpg",
            "Category": "movies",
            "Genres": [
                "Drama"
            ],
            "Rating": "N/A",
            "TMDb ID": 925943
        },
        "209646": {
            "Title": "Magic Mikes Last Dance",
            "Image Source": "https://i.imgur.com/WHmbiM4.jpg",
            "Category": "movies",
            "Genres": [
                "Drama",
                "Comedy"
            ],
            "Rating": "N/A",
            "TMDb ID": 906221
        },
        "209641": {
            "Title": "High Heat",
            "Image Source": "https://i.imgur.com/K6dhICr.jpg",
            "Category": "movies",
            "Genres": [
                "Action",
                "Crime",
                "Comedy"
            ],
            "Rating": "N/A",
            "TMDb ID": 1015963
        },
        "209636": {
            "Title": "Black Warrant",
            "Image Source": "https://i.imgur.com/hDFRU4r.jpg",
            "Category": "movies",
            "Genres": [
                "Action",
                "Thriller"
            ],
            "Rating": "N/A",
            "TMDb ID": 983768
        },
        "209632": {
            "Title": "Battle for Saipan",
            "Image Source": "https://i.imgur.com/TC8rJI6.jpg",
            "Category": "movies",
            "Genres": [
                "Action",
                "History",
                "War"
            ],
            "Rating": "N/A",
            "TMDb ID": 1037644
        }
    },
    "asian-series": {
        "208658": {
            "Title": "Taxi Driver",
            "Image Source": "https://imgpile.com/images/TPDrVl.jpg",
            "Category": "asian-series",
            "Genres": [
                "Action",
                "Crime",
                "Drama"
            ],
            "Rating": "N/A",
            "TMDb ID": 119769
        },
        "200508": {
            "Title": "Island",
            "Image Source": "https://i.imgur.com/dwc9A1L.jpg",
            "Category": "asian-series",
            "Genres": [
                "Action",
                "Adventure"
            ],
            "Rating": "7.1",
            "TMDb ID": 66636
        },
        "209913": {
            "Title": "Virgin",
            "Image Source": "https://i.imgur.com/nhzvrbz.jpg",
            "Category": "asian-series",
            "Genres": [
                "Drama"
            ],
            "Rating": "N/A",
            "TMDb ID": 73800
        },
        "209896": {
            "Title": "In the Name of God: A Holy Betrayal",
            "Image Source": "https://i.imgur.com/ZjsbGbA.jpg",
            "Category": "asian-series",
            "Genres": [
                "Crime",
                "Documentary"
            ],
            "Rating": "N/A",
            "TMDb ID": 218476
        },
        "206169": {
            "Title": "Nenek Bongkok Tiga",
            "Image Source": "https://i.imgur.com/srjsVws.jpg",
            "Category": "asian-series",
            "Genres": [
                "Thriller"
            ],
            "Rating": "N/A",
            "TMDb ID": 220080
        },
        "207773": {
            "Title": "The Heavenly Idol",
            "Image Source": "https://i.imgur.com/j59rAoL.jpg",
            "Category": "asian-series",
            "Genres": [
                "Romance"
            ],
            "Rating": "N/A",
            "TMDb ID": 202625
        },
        "209743": {
            "Title": "Delivery Man",
            "Image Source": "https://imgpile.com/images/TPDrVl.jpg",
            "Category": "asian-series",
            "Genres": [
                "Fantasy"
            ],
            "Rating": "N/A",
            "TMDb ID": 197081
        },
        "206189": {
            "Title": "Return Man",
            "Image Source": "https://i.imgur.com/q6AFuAm.jpg",
            "Category": "asian-series",
            "Genres": [
                "Comedy",
                "Mystery"
            ],
            "Rating": "N/A",
            "TMDb ID": 220047
        },
        "106890": {
            "Title": "Knowing Bros",
            "Image Source": "https://imgpile.com/images/TKcwfa.jpg",
            "Category": "asian-series",
            "Genres": [
                "Comedy",
                "Game-show",
                "Reality-tv"
            ],
            "Rating": "8.2",
            "TMDb ID": 70672
        }
    },
    "anime": {
        "202251": {
            "Title": "ISEKAI NONBIRI NOUKA",
            "Image Source": "https://i.imgur.com/k8LrQh3.jpg",
            "Category": "anime",
            "Genres": [
                "Animation",
                "Fantasy"
            ],
            "Rating": "7.36",
            "TMDb ID": 196285
        },
        "202266": {
            "Title": "Ars no kyojuu",
            "Image Source": "https://imgpile.com/images/dh5NJo.jpg",
            "Category": "anime",
            "Genres": [
                "Animation"
            ],
            "Rating": "6.78",
            "TMDb ID": 211093
        },
        "202599": {
            "Title": "Danmachi 4th Season Part 2",
            "Image Source": "https://i.imgur.com/p8H0sgF.jpg",
            "Category": "anime",
            "Genres": [
                "Animation",
                "Action",
                "Adventure"
            ],
            "Rating": "7.06",
            "TMDb ID": 70590
        },
        "199190": {
            "Title": "Oniichan Wa Oshimai!",
            "Image Source": "https://i.imgur.com/Myp6IhO.jpg",
            "Category": "anime",
            "Genres": [
                "Animation",
                "Comedy"
            ],
            "Rating": "7.31",
            "TMDb ID": 198152
        }
    },
    "series": {
        "209726": {
            "Title": "Wrong Side of the Tracks",
            "Image Source": "https://i.imgur.com/mNjlAYa.jpg",
            "Category": "series",
            "Genres": [
                "Action",
                "Crime",
                "Thriller"
            ],
            "Rating": "N/A",
            "TMDb ID": 128015
        },
        "209712": {
            "Title": "The Mandalorian",
            "Image Source": "https://i.imgur.com/iCbXDS8.jpg",
            "Category": "series",
            "Genres": [
                "Action",
                "Adventure",
                "Sci-fi"
            ],
            "Rating": "N/A",
            "TMDb ID": 82856
        },
        "209653": {
            "Title": "A Friend of the Family",
            "Image Source": "https://i.imgur.com/bSsYNj8.jpg",
            "Category": "series",
            "Genres": [
                "Biography",
                "Crime",
                "Drama"
            ],
            "Rating": "N/A",
            "TMDb ID": 197434
        },
        "209501": {
            "Title": "The Blacklist",
            "Image Source": "https://i.imgur.com/Lu6JtZG.jpg",
            "Category": "series",
            "Genres": [
                "Crime",
                "Drama",
                "Mystery",
                "Thriller"
            ],
            "Rating": "N/A",
            "TMDb ID": 46952
        },
        "209347": {
            "Title": "Liaison",
            "Image Source": "https://imgpile.com/images/TPDrVl.jpg",
            "Category": "series",
            "Genres": [
                "Thriller"
            ],
            "Rating": "N/A",
            "TMDb ID": 128066
        },
        "209344": {
            "Title": "Bel-Air",
            "Image Source": "https://imgpile.com/images/TPDrVl.jpg",
            "Category": "series",
            "Genres": [
                "Drama"
            ],
            "Rating": "N/A",
            "TMDb ID": 107365
        },
        "209295": {
            "Title": "Snowfall",
            "Image Source": "https://i.imgur.com/d9Pn9qK.jpg",
            "Category": "series",
            "Genres": [
                "Crime",
                "Drama"
            ],
            "Rating": "N/A",
            "TMDb ID": 71694
        },
        "209251": {
            "Title": "Outer Banks",
            "Image Source": "https://i.imgur.com/YOkYp5G.jpg",
            "Category": "series",
            "Genres": [
                "Drama"
            ],
            "Rating": "N/A",
            "TMDb ID": 100757
        },
        "208908": {
            "Title": "Magnum P.I.",
            "Image Source": "https://i.imgur.com/rr2xroL.jpg",
            "Category": "series",
            "Genres": [
                "Action",
                "Adventure",
                "Crime"
            ],
            "Rating": "N/A",
            "TMDb ID": 79593
        },
        "208685": {
            "Title": "La Cabeza de Joaqun Murrieta",
            "Image Source": "https://i.imgur.com/CdjlErB.jpg",
            "Category": "series",
            "Genres": [
                "Action",
                "Western"
            ],
            "Rating": "N/A",
            "TMDb ID": null
        },
        "208679": {
            "Title": "Wu Tang : An American Saga",
            "Image Source": "https://i.imgur.com/uBDLChv.jpg",
            "Category": "series",
            "Genres": [
                "Biography",
                "Drama"
            ],
            "Rating": "N/A",
            "TMDb ID": 90870
        },
        "186956": {
            "Title": "So Help Me Todd",
            "Image Source": "https://i.imgur.com/arFUucH.jpg",
            "Category": "series",
            "Genres": [
                "Drama"
            ],
            "Rating": "7.3",
            "TMDb ID": 202307
        },
        "187380": {
            "Title": "Alaska Daily",
            "Image Source": "https://i.imgur.com/FfniTvP.jpg",
            "Category": "series",
            "Genres": [
                "Drama"
            ],
            "Rating": "7.5",
            "TMDb ID": 201948
        },
        "205165": {
            "Title": "A Million Little Things",
            "Image Source": "https://imgpile.com/images/TPDrVl.jpg",
            "Category": "series",
            "Genres": [
                "Comedy",
                "Drama",
                "Mystery",
                "Romance"
            ],
            "Rating": "N/A",
            "TMDb ID": 81499
        },
        "186264": {
            "Title": "Abbott Elementary",
            "Image Source": "https://i.imgur.com/mZuIM3e.jpg",
            "Category": "series",
            "Genres": [
                "Comedy"
            ],
            "Rating": "8.2",
            "TMDb ID": 125935
        },
        "187446": {
            "Title": "Greys Anatomy",
            "Image Source": "https://i.imgur.com/gWBa9Zw.jpg",
            "Category": "series",
            "Genres": [
                "Drama",
                "Romance"
            ],
            "Rating": "7.6",
            "TMDb ID": 1416
        },
        "187449": {
            "Title": "Walker: Independence",
            "Image Source": "https://i.imgur.com/J2fGeDE.jpg",
            "Category": "series",
            "Genres": [
                "Action",
                "Crime"
            ],
            "Rating": "6.9",
            "TMDb ID": 201877
        }
    },
    "arabic-series": {
        "3976": {
            "Title": "بالطو",
            "Image Source": "https://i.imgur.com/FFI13Xm.jpg",
            "Category": "arabic-series"
        },
        "3989": {
            "Title": "دهب بنت الأوتيل",
            "Image Source": "https://i.imgur.com/xJLUmsr.jpg",
            "Category": "arabic-series"
        },
        "3978": {
            "Title": "ولاد العم الموسم الثاني",
            "Image Source": "https://i.imgur.com/Dtq0MFp.jpg",
            "Category": "arabic-series"
        },
        "3988": {
            "Title": "تياترو",
            "Image Source": "https://i.imgur.com/BlKC7Pr.jpg",
            "Category": "arabic-series"
        }
    },
    "arabic-movies": {
        "8087": {
            "Title": "خطة مازنجر",
            "Image Source": "https://i.imgur.com/64Ct1Dd.jpg",
            "Category": "arabic-movies"
        },
        "8059": {
            "Title": "حظك اليوم",
            "Image Source": "https://i.imgur.com/hLRnodK.jpg",
            "Category": "arabic-movies"
        }
    }
}